<?xml version = '1.0' encoding = 'UTF-8'?>
<TableProxyOraclev12c class="oracle.dbtools.crest.model.design.storage.oracle.v12c.TableProxyOraclev12c" name="PRODUK_ITEM" directorySegmentName="seg_0" id="2D40A9A4-E052-2DA0-68E8-A03104F68EE4">
<createdBy>FransMa</createdBy>
<createdTime>2019-10-28 02:54:56 UTC</createdTime>
<ownerDesignName>pppc_prodfdi</ownerDesignName>
<schemaObject>C9391DEC-BBF6-7C19-FA2A-D5CF4AE93BE9</schemaObject>
<logging>YES</logging>
<partitionedRowMovement>DISABLE</partitionedRowMovement>
<segment>10432B3F-6321-DE84-7974-B7217C845E2F</segment>
<tableSpace>D0CEBD5F-FDB7-6CEA-EAA5-4B81F8B8B91B</tableSpace>
<temporaryChanged>false</temporaryChanged>
<accessDriverType>oracle_loader</accessDriverType>
<rejectLimit></rejectLimit>
<inMemory>NO</inMemory>
<columnProxies itemClass="oracle.dbtools.crest.model.design.storage.oracle.v12c.ColumnProxyOraclev12c">
<ColumnProxy name="PROMO_PRODUK_ID" id="37B63C45-7127-69C9-7871-80CBFDAFD3CA">
<createdBy>FransMa</createdBy>
<createdTime>2019-10-28 02:54:58 UTC</createdTime>
<ownerDesignName>pppc_prodfdi</ownerDesignName>
</ColumnProxy>
<ColumnProxy name="PROD_ITEM" id="73BAD4F4-E930-8C01-DA4B-C2CE1DCFF35A">
<createdBy>FransMa</createdBy>
<createdTime>2019-10-28 02:54:58 UTC</createdTime>
<ownerDesignName>pppc_prodfdi</ownerDesignName>
</ColumnProxy>
<ColumnProxy name="ITEM_DESC" id="99374DC9-F88E-4B69-D51A-6CDAE6049B7A">
<createdBy>FransMa</createdBy>
<createdTime>2019-10-28 02:54:58 UTC</createdTime>
<ownerDesignName>pppc_prodfdi</ownerDesignName>
</ColumnProxy>
</columnProxies>
<indexProxies>
<IndexProxy class="oracle.dbtools.crest.model.design.storage.oracle.v10g.IndexProxyOraclev10g" name="PRODUK_ITEM_PK" id="097FFE31-AC5D-DA9A-8B56-B0F46E481C32">
<createdBy>FransMa</createdBy>
<createdTime>2019-10-28 02:55:00 UTC</createdTime>
<ownerDesignName>pppc_prodfdi</ownerDesignName>
<schemaObject>C9391DEC-BBF6-7C19-FA2A-D5CF4AE93BE9</schemaObject>
<segment>09BD77D0-976B-949D-3711-8EFC02F9D44F</segment>
<tableSpace>D0CEBD5F-FDB7-6CEA-EAA5-4B81F8B8B91B</tableSpace>
</IndexProxy>
</indexProxies>
<primaryKeys>
<PrimaryKey class="oracle.dbtools.crest.model.design.storage.oracle.v10g.PKProxyOraclev10g" name="PRODUK_ITEM_PK" id="1C6DB74C-4D97-2928-66E6-1FAE4EBF2D6B">
<createdBy>FransMa</createdBy>
<createdTime>2019-10-28 02:55:02 UTC</createdTime>
<ownerDesignName>pppc_prodfdi</ownerDesignName>
<segment>09BD77D0-976B-949D-3711-8EFC02F9D44F</segment>
<tableSpace>D0CEBD5F-FDB7-6CEA-EAA5-4B81F8B8B91B</tableSpace>
<existingIndex>097FFE31-AC5D-DA9A-8B56-B0F46E481C32</existingIndex>
<indexSegment>09BD77D0-976B-949D-3711-8EFC02F9D44F</indexSegment>
<indexSort>SORTED</indexSort>
<usingIndex>BY INDEX NAME</usingIndex>
</PrimaryKey>
</primaryKeys>
</TableProxyOraclev12c>