<?xml version = '1.0' encoding = 'UTF-8'?>
<SegmentOraclev10g class="oracle.dbtools.crest.model.design.storage.oracle.v10g.SegmentOraclev10g" name="Storage115" directorySegmentName="seg_0" id="7A740EBA-B45C-7219-2B3C-125B8A2FB087">
<createdBy>frans</createdBy>
<createdTime>2019-04-30 09:52:38 UTC</createdTime>
<ownerDesignName>pppc_model</ownerDesignName>
<maxTrans>255</maxTrans>
<scInitialExtent>65536</scInitialExtent>
<scMaxExtents>2147483645</scMaxExtents>
<scNextExtent>1064960</scNextExtent>
</SegmentOraclev10g>