<?xml version = '1.0' encoding = 'UTF-8'?>
<SegmentOraclev10g class="oracle.dbtools.crest.model.design.storage.oracle.v10g.SegmentOraclev10g" name="Storage1" directorySegmentName="seg_0" id="835E9FBE-F97D-6AEF-C032-096BD61638FB">
<createdBy>frans</createdBy>
<createdTime>2019-04-30 09:52:35 UTC</createdTime>
<ownerDesignName>pppc_model</ownerDesignName>
<maxTrans>255</maxTrans>
<scInitialExtent>327680</scInitialExtent>
<scMaxExtents>2147483645</scMaxExtents>
<scNextExtent>1048576</scNextExtent>
<scPctIncrease>50</scPctIncrease>
</SegmentOraclev10g>