<?xml version = '1.0' encoding = 'UTF-8'?>
<SegmentOraclev10g class="oracle.dbtools.crest.model.design.storage.oracle.v10g.SegmentOraclev10g" name="Storage69" directorySegmentName="seg_0" id="FCF9FD40-4E68-3E82-8109-259545F034D5">
<createdBy>frans</createdBy>
<createdTime>2019-04-30 09:52:36 UTC</createdTime>
<ownerDesignName>pppc_model</ownerDesignName>
<maxTrans>255</maxTrans>
<scInitialExtent>65536</scInitialExtent>
<scMaxExtents>2147483645</scMaxExtents>
<scNextExtent>2359296</scNextExtent>
<scPctIncrease>50</scPctIncrease>
</SegmentOraclev10g>