<?xml version = '1.0' encoding = 'UTF-8'?>
<FKIndexAssociation class="oracle.dbtools.crest.model.design.relational.FKIndexAssociation" directorySegmentName="seg_0" id="481B4798-6072-D35E-1C7D-108894970AEF" containerWithKeyObject="1A1256E0-7309-3C68-4928-54233E00BF36" localFKIndex="F5E51D69-CEB5-E8F8-207F-8F3F330B1C6F" name="PROD_REGION_CUST_TYPE_PRO_FK1">
<sourceConnName>pppc@uatfdi</sourceConnName>
<sourceObjSchema>FOCUSPP</sourceObjSchema>
<sourceObjName>PROD_REGION_CUST_TYPE_PRO_FK1</sourceObjName>
<createdBy>frans</createdBy>
<createdTime>2019-04-30 09:54:23 UTC</createdTime>
<ownerDesignName>pppc_model</ownerDesignName>
<referredTableLongName>FOCUSPP.PROMO_PRODUK</referredTableLongName>
<deleteRule>CASCADE</deleteRule>
<referredTableID>91E05B52-035E-2397-2209-933F68A754F2</referredTableID>
<keyObject>754EE4E3-2E9B-F32D-4663-0B5824FDE9D0</keyObject>
<referredKeyID>754EE4E3-2E9B-F32D-4663-0B5824FDE9D0</referredKeyID>
<mandatory>true</mandatory>
<refColNames>PROMO_PRODUK_ID</refColNames>
<transferable>true</transferable>
<rely>false</rely>
<columnDependencyConstraintGenerateInDDL>true</columnDependencyConstraintGenerateInDDL>
</FKIndexAssociation>